llmnet/__init__.py
llmnet/blueprints/__init__.py
llmnet/blueprints/botnet.py
llmnet/blueprints/constants.py
llmnet/llms/__init__.py
llmnet/llms/combined.py
llmnet/llms/googlegate.py
llmnet/llms/openaigate.py
llmnet/observer/__init__.py
llmnet/observer/tracker.py
llmnet/process/__init__.py
llmnet/process/multi.py
llmnet-0.1.1.dist-info/LICENSE
llmnet-0.1.1.dist-info/METADATA
llmnet-0.1.1.dist-info/WHEEL
llmnet-0.1.1.dist-info/top_level.txt
llmnet-0.1.1.dist-info/RECORD
