Metadata-Version: 2.1
Name: llmnet
Version: 0.1.1
Summary: A library designed to harness the diversity of thought by combining multiple LLMs.
Home-page: https://github.com/maxmekiska/llmnet
Author: Maximilian Mekiska
Author-email: maxmekiska@gmail.com
License: UNKNOWN
Keywords: machinelearning,llm,bots,network
Platform: UNKNOWN
Classifier: Programming Language :: Python :: 3.9
Classifier: Programming Language :: Python :: 3.10
Classifier: Programming Language :: Python :: 3.11
Classifier: Topic :: Scientific/Engineering :: Artificial Intelligence
Requires-Dist: openai <=0.28,>=0.27.5
Requires-Dist: google-generativeai <=0.4.0,>=0.3.1
